ddlcli/__init__.py
ddlcli/cli.py
ddlcli/constants.py
ddlcli/job.py
ddlcli/s3_util.py
ddlcli/user.py
ddlcli/utils.py
ddlcli-0.0.5.dist-info/METADATA
ddlcli-0.0.5.dist-info/RECORD
ddlcli-0.0.5.dist-info/WHEEL
ddlcli-0.0.5.dist-info/entry_points.txt
ddlcli-0.0.5.dist-info/top_level.txt
