Metadata-Version: 2.1
Name: ddlcli
Version: 0.0.5
Summary: cli for distributed deep learning
Home-page: UNKNOWN
Author: Yi Lu
License: UNKNOWN
Platform: UNKNOWN
Classifier: Programming Language :: Python :: 3
Classifier: License :: OSI Approved :: MIT License
Classifier: Operating System :: OS Independent
Requires-Dist: pyyaml
Requires-Dist: boto3
Requires-Dist: requests
